MANIFEST.in
README.md
setup.py
donations/__init__.py
donations/admin.py
donations/app_registry.py
donations/forms.py
donations/management.py
donations/managers.py
donations/models.py
donations/search_indexes.py
donations/settings.json
donations/signals.py
donations/urls.py
donations/utils.py
donations/views.py
donations/migrations/0001_initial.py
donations/migrations/__init__.py
donations/static/css/donations.css
donations/templates/donations/add.html
donations/templates/donations/add_confirm.html
donations/templates/donations/base.html
donations/templates/donations/email_user.txt
donations/templates/donations/email_user_subject.txt
donations/templates/donations/invoice_search_result_line.html
donations/templates/donations/invoice_view_display.html
donations/templates/donations/nav.html
donations/templates/donations/payment_thankyou_display.html
donations/templates/donations/payment_thankyou_header.html
donations/templates/donations/receipt.html
donations/templates/donations/search-form.html
donations/templates/donations/search.html
donations/templates/donations/view.html
donations/templates/search/indexes/donations/donation_text.txt
donations/templatetags/__init__.py
donations/templatetags/donation_tags.py
tendenci_donations.egg-info/PKG-INFO
tendenci_donations.egg-info/SOURCES.txt
tendenci_donations.egg-info/dependency_links.txt
tendenci_donations.egg-info/requires.txt
tendenci_donations.egg-info/top_level.txt